setup.py
utilities/__init__.py
utilities/api.py
utilities/configs.py
utilities/crypto.py
utilities/fs.py
utilities/networking.py
utilities/platform.py
utilities/services.py
utilities/simple_templating.py
utilities/system.py
utilities/templating.py
utilities_package.egg-info/PKG-INFO
utilities_package.egg-info/SOURCES.txt
utilities_package.egg-info/dependency_links.txt
utilities_package.egg-info/not-zip-safe
utilities_package.egg-info/requires.txt
utilities_package.egg-info/top_level.txt