Metadata-Version: 1.0
Name: utilities-package
Version: 0.0.6
Summary: utilities package
Home-page: https://github.com/terminal-labs/utilities
Author: Terminal Labs
Author-email: solutions@terminallabs.com
License: license
Platform: UNKNOWN
